openai_to_sqlite/__init__.py
openai_to_sqlite/__main__.py
openai_to_sqlite/cli.py
openai_to_sqlite-0.4.2.dist-info/LICENSE
openai_to_sqlite-0.4.2.dist-info/METADATA
openai_to_sqlite-0.4.2.dist-info/WHEEL
openai_to_sqlite-0.4.2.dist-info/entry_points.txt
openai_to_sqlite-0.4.2.dist-info/top_level.txt
openai_to_sqlite-0.4.2.dist-info/RECORD
