Metadata-Version: 2.1
Name: openai-to-sqlite
Version: 0.4.2
Summary: Save OpenAI API results to a SQLite database
Home-page: https://github.com/simonw/openai-to-sqlite
Author: Simon Willison
License: Apache License, Version 2.0
Project-URL: Issues, https://github.com/simonw/openai-to-sqlite/issues
Project-URL: CI, https://github.com/simonw/openai-to-sqlite/actions
Project-URL: Changelog, https://github.com/simonw/openai-to-sqlite/releases
Requires-Python: >=3.8
License-File: LICENSE
Requires-Dist: click
Requires-Dist: httpx
Requires-Dist: sqlite-utils >=3.28
Requires-Dist: openai
Requires-Dist: tiktoken
Provides-Extra: test
Requires-Dist: pytest ; extra == 'test'
Requires-Dist: pytest-httpx ; extra == 'test'
Requires-Dist: pytest-mock ; extra == 'test'
